projectZ/__init__.py
projectZ/async_client.py
projectZ/client.py
projectZ/requests_builder.py
projectZ/objects/ChatMessageTypes.py
projectZ/objects/MediaTargets.py
projectZ/objects/__init__.py
projectZ/objects/constants.py
projectZ/objects/objects.py
projectZ/objects/profile.py
projectZ/objects/ws_types.py
projectZ/utils/__init__.py
projectZ/utils/exceptions.py
projectZ/utils/generator.py
projectZ/ws/__init__.py
projectZ/ws/async_socket.py
projectZ/ws/socket.py
projectZ-1.1.7.2.1.4.dist-info/LICENSE.txt
projectZ-1.1.7.2.1.4.dist-info/METADATA
projectZ-1.1.7.2.1.4.dist-info/WHEEL
projectZ-1.1.7.2.1.4.dist-info/top_level.txt
projectZ-1.1.7.2.1.4.dist-info/RECORD
