Metadata-Version: 2.1
Name: projectZ
Version: 1.1.7.2.1.4
Summary: Library for creating projectZ bots and scripts.
Home-page: https://github.com/xXxCLOTIxXx/projectZ.py
Download-URL: https://github.com/xXxCLOTIxXx/projectZ.py/archive/refs/heads/main.zip
Author: Xsarz
Author-email: xsarzy@gmail.com
License: MIT
Keywords: projectZ.py,projectZ,projectZ-py,projectZ-bot,api,python,python3,python3.x,xsarz,official,async,sync,projz
License-File: LICENSE.txt
Requires-Dist: aiofiles
Requires-Dist: aiohttp
Requires-Dist: requests
Requires-Dist: ujson
Requires-Dist: websocket-client
